pgrubic/__init__.py
pgrubic/__main__.py
pgrubic/pgrubic.toml
pgrubic/py.typed
pgrubic/core/__init__.py
pgrubic/core/cache.py
pgrubic/core/config.py
pgrubic/core/enums.py
pgrubic/core/errors.py
pgrubic/core/filters.py
pgrubic/core/formatter.py
pgrubic/core/linter.py
pgrubic/core/loader.py
pgrubic/core/logger.py
pgrubic/core/noqa.py
pgrubic/core/visitors.py
pgrubic/formatters/__init__.py
pgrubic/formatters/ddl/__init__.py
pgrubic/formatters/ddl/column.py
pgrubic/formatters/ddl/constraint.py
pgrubic/formatters/ddl/database.py
pgrubic/formatters/ddl/enum.py
pgrubic/formatters/ddl/function.py
pgrubic/formatters/ddl/index.py
pgrubic/formatters/ddl/owner.py
pgrubic/formatters/ddl/rename.py
pgrubic/formatters/ddl/schema.py
pgrubic/formatters/ddl/table.py
pgrubic/formatters/ddl/view.py
pgrubic/formatters/dml/__init__.py
pgrubic/formatters/dml/boolean.py
pgrubic/formatters/dml/cte.py
pgrubic/formatters/dml/delete.py
pgrubic/formatters/dml/insert.py
pgrubic/formatters/dml/join.py
pgrubic/formatters/dml/select.py
pgrubic/formatters/dml/update.py
pgrubic/rules/__init__.py
pgrubic/rules/constraint/CT001.py
pgrubic/rules/constraint/CT002.py
pgrubic/rules/constraint/CT003.py
pgrubic/rules/constraint/CT004.py
pgrubic/rules/constraint/CT005.py
pgrubic/rules/constraint/CT006.py
pgrubic/rules/constraint/__init__.py
pgrubic/rules/general/GN001.py
pgrubic/rules/general/GN002.py
pgrubic/rules/general/GN003.py
pgrubic/rules/general/GN004.py
pgrubic/rules/general/GN005.py
pgrubic/rules/general/GN006.py
pgrubic/rules/general/GN007.py
pgrubic/rules/general/GN008.py
pgrubic/rules/general/GN009.py
pgrubic/rules/general/GN010.py
pgrubic/rules/general/GN011.py
pgrubic/rules/general/GN012.py
pgrubic/rules/general/GN013.py
pgrubic/rules/general/GN014.py
pgrubic/rules/general/GN015.py
pgrubic/rules/general/GN016.py
pgrubic/rules/general/GN017.py
pgrubic/rules/general/GN018.py
pgrubic/rules/general/GN019.py
pgrubic/rules/general/GN020.py
pgrubic/rules/general/GN021.py
pgrubic/rules/general/GN022.py
pgrubic-0.9.0.dist-info/licenses/LICENSE
pgrubic-0.9.0.dist-info/METADATA
pgrubic-0.9.0.dist-info/WHEEL
pgrubic-0.9.0.dist-info/entry_points.txt
pgrubic-0.9.0.dist-info/top_level.txt
pgrubic-0.9.0.dist-info/RECORD
