Metadata-Version: 2.4
Name: pgrubic
Version: 0.9.0
Summary: PostgreSQL linter and formatter for schema migrations and design best practices
Author-email: Bolaji Wahab <bolajiwahab23@gmail.com>
Maintainer-email: Bolaji Wahab <bolajiwahab23@gmail.com>
License-Expression: GPL-3.0-or-later
Project-URL: Homepage, https://github.com/bolajiwahab/pgrubic
Project-URL: Documentation, https://github.com/bolajiwahab/pgrubic/blob/main/README.md
Project-URL: Repository, https://github.com/bolajiwahab/pgrubic
Project-URL: Issue Tracker, https://github.com/bolajiwahab/pgrubic/issues
Project-URL: Changelog, https://github.com/bolajiwahab/pgrubic/blob/main/CHANGELOG.md
Keywords: pgrubic,sql,postgres,postgresql,linter
Classifier: Development Status :: 4 - Beta
Classifier: Environment :: Console
Classifier: Intended Audience :: Developers
Classifier: Operating System :: MacOS :: MacOS X
Classifier: Operating System :: POSIX :: Linux
Classifier: Operating System :: Microsoft :: Windows
Classifier: Programming Language :: Python
Classifier: Programming Language :: Python :: 3
Classifier: Programming Language :: Python :: 3.12
Classifier: Programming Language :: Python :: 3.13
Classifier: Programming Language :: SQL
Classifier: Topic :: Database
Classifier: Topic :: Utilities
Classifier: Topic :: Software Development :: Quality Assurance
Requires-Python: >=3.12
License-File: LICENSE
Requires-Dist: pglast==7.7
Requires-Dist: case-converter==1.2.0
Requires-Dist: colorama==0.4.6
Requires-Dist: toml==0.10.2
Requires-Dist: click==8.2.1
Requires-Dist: rich==14.1.0
Requires-Dist: deepmerge==2.0
Requires-Dist: msgpack==1.1.1
Requires-Dist: GitPython==3.1.45
Provides-Extra: dev
Requires-Dist: ruff==0.12.10; extra == "dev"
Requires-Dist: mypy==1.17.1; extra == "dev"
Requires-Dist: isort==6.0.1; extra == "dev"
Requires-Dist: bandit==1.8.6; extra == "dev"
Requires-Dist: add-trailing-comma==3.2.0; extra == "dev"
Requires-Dist: interrogate==1.7.0; extra == "dev"
Requires-Dist: pre-commit==4.3.0; extra == "dev"
Requires-Dist: pre-commit-hooks==6.0.0; extra == "dev"
Requires-Dist: yamllint==1.37.1; extra == "dev"
Requires-Dist: conventional-pre-commit==4.2.0; extra == "dev"
Requires-Dist: pytest==8.4.1; extra == "dev"
Requires-Dist: coverage==7.10.5; extra == "dev"
Requires-Dist: tox==4.28.4; extra == "dev"
Requires-Dist: types-PyYAML==6.0.12.20250822; extra == "dev"
Requires-Dist: types-toml==0.10.8.20240310; extra == "dev"
Requires-Dist: types-colorama==0.4.15.20250801; extra == "dev"
Requires-Dist: types-click==7.1.8; extra == "dev"
Requires-Dist: msgpack-types==0.5.0; extra == "dev"
Provides-Extra: doc
Requires-Dist: mkdocs==1.6.1; extra == "doc"
Requires-Dist: mkdocs-material==9.6.18; extra == "doc"
Requires-Dist: mkdocstrings==0.30.0; extra == "doc"
Requires-Dist: mkdocstrings-python==1.17.0; extra == "doc"
Provides-Extra: release
Requires-Dist: commitizen==4.8.3; extra == "release"
Dynamic: license-file
